heflwr/__init__.py
heflwr/fed/__init__.py
heflwr/fed/aggregate.py
heflwr/fed/he_client_manager.py
heflwr/fed/heflwr_aggregate.py
heflwr/fed/heflwr_client_manager.py
heflwr/fed/hetero_aggregate.py
heflwr/log/__init__.py
heflwr/log/configurator.py
heflwr/log/handlers.py
heflwr/log/log_info.py
heflwr/log/logger.py
heflwr/monitor/__init__.py
heflwr/monitor/process_monitor/__init__.py
heflwr/monitor/process_monitor/file_monitor.py
heflwr/monitor/process_monitor/prometheus_monitor.py
heflwr/monitor/process_monitor/remote_monitor.py
heflwr/monitor/thread_monitor/__init__.py
heflwr/monitor/thread_monitor/file_monitor.py
heflwr/monitor/thread_monitor/prometheus_monitor.py
heflwr/monitor/thread_monitor/remote_monitor.py
heflwr/monitor/utils/__init__.py
heflwr/monitor/utils/network.py
heflwr/monitor/utils/power.py
heflwr/nn/__init__.py
heflwr/nn/rnn.py
heflwr/nn/scaler.py
heflwr/nn/ssbatchnorm2d.py
heflwr/nn/ssconv2d.py
heflwr/nn/sslinear.py
heflwr/nn/utils.py
heflwr-0.1.91.dist-info/LICENSE
heflwr-0.1.91.dist-info/METADATA
heflwr-0.1.91.dist-info/WHEEL
heflwr-0.1.91.dist-info/top_level.txt
heflwr-0.1.91.dist-info/RECORD
