Metadata-Version: 2.1
Name: heflwr
Version: 0.1.91
Summary: 「HeFlwr」is a federated learning package for heterogeneous devices.
Home-page: https://github.com/QVQZZZ/HeFlwr
Author: Zhu Yaolin
Author-email: zhuyaolinluck@qq.com
License: MIT
License-File: LICENSE
Requires-Dist: psutil (<7.0.0,>=5.9.0)
Requires-Dist: prometheus-client (<1.0.0,>=0.17.0)
